seqLister/__init__.py
seqLister-1.2.0.dist-info/LICENSE
seqLister-1.2.0.dist-info/METADATA
seqLister-1.2.0.dist-info/WHEEL
seqLister-1.2.0.dist-info/top_level.txt
seqLister-1.2.0.dist-info/RECORD
